loggly/__init__.py
loggly/handlers.py
loggly_python_handler-1.0.1.dist-info/LICENSE
loggly_python_handler-1.0.1.dist-info/METADATA
loggly_python_handler-1.0.1.dist-info/WHEEL
loggly_python_handler-1.0.1.dist-info/top_level.txt
loggly_python_handler-1.0.1.dist-info/RECORD
