Metadata-Version: 2.1
Name: loggly-python-handler
Version: 1.0.1
Summary: Python logging handler that sends messages to Loggly
Home-page: https://github.com/loggly/loggly-python-handler/
Author: Loggly
Author-email: support@loggly.com
License: MIT
Keywords: loggly logging handler https
Platform: UNKNOWN
Classifier: License :: OSI Approved :: MIT License
Classifier: Development Status :: 4 - Beta
Classifier: Intended Audience :: Developers
Requires-Dist: requests-futures (>=1.0.0)
